{
 "ap-northeast-1": {
  "enum": [
   "stream.compute.2xlarge",
   "stream.compute.4xlarge",
   "stream.compute.8xlarge",
   "stream.compute.large",
   "stream.compute.xlarge",
   "stream.graphics-design.2xlarge",
   "stream.graphics-design.4xlarge",
   "stream.graphics-design.large",
   "stream.graphics-design.xlarge",
   "stream.graphics-pro.16xlarge",
   "stream.graphics-pro.4xlarge",
   "stream.graphics-pro.8xlarge",
   "stream.graphics.g4dn.12xlarge",
   "stream.graphics.g4dn.16xlarge",
   "stream.graphics.g4dn.2xlarge",
   "stream.graphics.g4dn.4xlarge",
   "stream.graphics.g4dn.8xlarge",
   "stream.graphics.g4dn.xlarge",
   "stream.graphics.g5.12xlarge",
   "stream.graphics.g5.16xlarge",
   "stream.graphics.g5.24xlarge",
   "stream.graphics.g5.2xlarge",
   "stream.graphics.g5.4xlarge",
   "stream.graphics.g5.8xlarge",
   "stream.graphics.g5.xlarge",
   "stream.memory.2xlarge",
   "stream.memory.4xlarge",
   "stream.memory.8xlarge",
   "stream.memory.large",
   "stream.memory.xlarge",
   "stream.memory.z1d.12xlarge",
   "stream.memory.z1d.2xlarge",
   "stream.memory.z1d.3xlarge",
   "stream.memory.z1d.6xlarge",
   "stream.memory.z1d.large",
   "stream.memory.z1d.xlarge",
   "stream.standard.2xlarge",
   "stream.standard.large",
   "stream.standard.medium",
   "stream.standard.small",
   "stream.standard.xlarge"
  ]
 },
 "ap-northeast-2": {
  "enum": [
   "stream.compute.2xlarge",
   "stream.compute.4xlarge",
   "stream.compute.8xlarge",
   "stream.compute.large",
   "stream.compute.xlarge",
   "stream.graphics-design.2xlarge",
   "stream.graphics-design.4xlarge",
   "stream.graphics-design.large",
   "stream.graphics-design.xlarge",
   "stream.graphics-pro.16xlarge",
   "stream.graphics-pro.4xlarge",
   "stream.graphics-pro.8xlarge",
   "stream.graphics.g4dn.12xlarge",
   "stream.graphics.g4dn.16xlarge",
   "stream.graphics.g4dn.2xlarge",
   "stream.graphics.g4dn.4xlarge",
   "stream.graphics.g4dn.8xlarge",
   "stream.graphics.g4dn.xlarge",
   "stream.graphics.g5.12xlarge",
   "stream.graphics.g5.16xlarge",
   "stream.graphics.g5.24xlarge",
   "stream.graphics.g5.2xlarge",
   "stream.graphics.g5.4xlarge",
   "stream.graphics.g5.8xlarge",
   "stream.graphics.g5.xlarge",
   "stream.memory.2xlarge",
   "stream.memory.4xlarge",
   "stream.memory.8xlarge",
   "stream.memory.large",
   "stream.memory.xlarge",
   "stream.memory.z1d.12xlarge",
   "stream.memory.z1d.2xlarge",
   "stream.memory.z1d.3xlarge",
   "stream.memory.z1d.6xlarge",
   "stream.memory.z1d.large",
   "stream.memory.z1d.xlarge",
   "stream.standard.2xlarge",
   "stream.standard.large",
   "stream.standard.medium",
   "stream.standard.small",
   "stream.standard.xlarge"
  ]
 },
 "ap-south-1": {
  "enum": [
   "stream.compute.2xlarge",
   "stream.compute.4xlarge",
   "stream.compute.8xlarge",
   "stream.compute.large",
   "stream.compute.xlarge",
   "stream.graphics-design.2xlarge",
   "stream.graphics-design.4xlarge",
   "stream.graphics-design.large",
   "stream.graphics-design.xlarge",
   "stream.graphics-pro.16xlarge",
   "stream.graphics-pro.4xlarge",
   "stream.graphics-pro.8xlarge",
   "stream.graphics.g4dn.12xlarge",
   "stream.graphics.g4dn.16xlarge",
   "stream.graphics.g4dn.2xlarge",
   "stream.graphics.g4dn.4xlarge",
   "stream.graphics.g4dn.8xlarge",
   "stream.graphics.g4dn.xlarge",
   "stream.graphics.g5.12xlarge",
   "stream.graphics.g5.16xlarge",
   "stream.graphics.g5.24xlarge",
   "stream.graphics.g5.2xlarge",
   "stream.graphics.g5.4xlarge",
   "stream.graphics.g5.8xlarge",
   "stream.graphics.g5.xlarge",
   "stream.memory.2xlarge",
   "stream.memory.4xlarge",
   "stream.memory.8xlarge",
   "stream.memory.large",
   "stream.memory.xlarge",
   "stream.memory.z1d.12xlarge",
   "stream.memory.z1d.2xlarge",
   "stream.memory.z1d.3xlarge",
   "stream.memory.z1d.6xlarge",
   "stream.memory.z1d.large",
   "stream.memory.z1d.xlarge",
   "stream.standard.2xlarge",
   "stream.standard.large",
   "stream.standard.medium",
   "stream.standard.small",
   "stream.standard.xlarge"
  ]
 },
 "ap-southeast-1": {
  "enum": [
   "stream.compute.2xlarge",
   "stream.compute.4xlarge",
   "stream.compute.8xlarge",
   "stream.compute.large",
   "stream.compute.xlarge",
   "stream.graphics-design.2xlarge",
   "stream.graphics-design.4xlarge",
   "stream.graphics-design.large",
   "stream.graphics-design.xlarge",
   "stream.graphics-pro.16xlarge",
   "stream.graphics-pro.4xlarge",
   "stream.graphics-pro.8xlarge",
   "stream.graphics.g4dn.12xlarge",
   "stream.graphics.g4dn.16xlarge",
   "stream.graphics.g4dn.2xlarge",
   "stream.graphics.g4dn.4xlarge",
   "stream.graphics.g4dn.8xlarge",
   "stream.graphics.g4dn.xlarge",
   "stream.graphics.g5.12xlarge",
   "stream.graphics.g5.16xlarge",
   "stream.graphics.g5.24xlarge",
   "stream.graphics.g5.2xlarge",
   "stream.graphics.g5.4xlarge",
   "stream.graphics.g5.8xlarge",
   "stream.graphics.g5.xlarge",
   "stream.memory.2xlarge",
   "stream.memory.4xlarge",
   "stream.memory.8xlarge",
   "stream.memory.large",
   "stream.memory.xlarge",
   "stream.memory.z1d.12xlarge",
   "stream.memory.z1d.2xlarge",
   "stream.memory.z1d.3xlarge",
   "stream.memory.z1d.6xlarge",
   "stream.memory.z1d.large",
   "stream.memory.z1d.xlarge",
   "stream.standard.2xlarge",
   "stream.standard.large",
   "stream.standard.medium",
   "stream.standard.small",
   "stream.standard.xlarge"
  ]
 },
 "ap-southeast-2": {
  "enum": [
   "stream.compute.2xlarge",
   "stream.compute.4xlarge",
   "stream.compute.8xlarge",
   "stream.compute.large",
   "stream.compute.xlarge",
   "stream.graphics-design.2xlarge",
   "stream.graphics-design.4xlarge",
   "stream.graphics-design.large",
   "stream.graphics-design.xlarge",
   "stream.graphics-pro.16xlarge",
   "stream.graphics-pro.4xlarge",
   "stream.graphics-pro.8xlarge",
   "stream.graphics.g4dn.12xlarge",
   "stream.graphics.g4dn.16xlarge",
   "stream.graphics.g4dn.2xlarge",
   "stream.graphics.g4dn.4xlarge",
   "stream.graphics.g4dn.8xlarge",
   "stream.graphics.g4dn.xlarge",
   "stream.graphics.g5.12xlarge",
   "stream.graphics.g5.16xlarge",
   "stream.graphics.g5.24xlarge",
   "stream.graphics.g5.2xlarge",
   "stream.graphics.g5.4xlarge",
   "stream.graphics.g5.8xlarge",
   "stream.graphics.g5.xlarge",
   "stream.memory.2xlarge",
   "stream.memory.4xlarge",
   "stream.memory.8xlarge",
   "stream.memory.large",
   "stream.memory.xlarge",
   "stream.memory.z1d.12xlarge",
   "stream.memory.z1d.2xlarge",
   "stream.memory.z1d.3xlarge",
   "stream.memory.z1d.6xlarge",
   "stream.memory.z1d.large",
   "stream.memory.z1d.xlarge",
   "stream.standard.2xlarge",
   "stream.standard.large",
   "stream.standard.medium",
   "stream.standard.small",
   "stream.standard.xlarge"
  ]
 },
 "ca-central-1": {
  "enum": [
   "stream.compute.2xlarge",
   "stream.compute.4xlarge",
   "stream.compute.8xlarge",
   "stream.compute.large",
   "stream.compute.xlarge",
   "stream.graphics-design.2xlarge",
   "stream.graphics-design.4xlarge",
   "stream.graphics-design.large",
   "stream.graphics-design.xlarge",
   "stream.graphics-pro.16xlarge",
   "stream.graphics-pro.4xlarge",
   "stream.graphics-pro.8xlarge",
   "stream.graphics.g4dn.12xlarge",
   "stream.graphics.g4dn.16xlarge",
   "stream.graphics.g4dn.2xlarge",
   "stream.graphics.g4dn.4xlarge",
   "stream.graphics.g4dn.8xlarge",
   "stream.graphics.g4dn.xlarge",
   "stream.graphics.g5.12xlarge",
   "stream.graphics.g5.16xlarge",
   "stream.graphics.g5.24xlarge",
   "stream.graphics.g5.2xlarge",
   "stream.graphics.g5.4xlarge",
   "stream.graphics.g5.8xlarge",
   "stream.graphics.g5.xlarge",
   "stream.memory.2xlarge",
   "stream.memory.4xlarge",
   "stream.memory.8xlarge",
   "stream.memory.large",
   "stream.memory.xlarge",
   "stream.memory.z1d.12xlarge",
   "stream.memory.z1d.2xlarge",
   "stream.memory.z1d.3xlarge",
   "stream.memory.z1d.6xlarge",
   "stream.memory.z1d.large",
   "stream.memory.z1d.xlarge",
   "stream.standard.2xlarge",
   "stream.standard.large",
   "stream.standard.medium",
   "stream.standard.small",
   "stream.standard.xlarge"
  ]
 },
 "description": "Automatically updated using update_specs_from_pricing",
 "eu-central-1": {
  "enum": [
   "stream.compute.2xlarge",
   "stream.compute.4xlarge",
   "stream.compute.8xlarge",
   "stream.compute.large",
   "stream.compute.xlarge",
   "stream.graphics-design.2xlarge",
   "stream.graphics-design.4xlarge",
   "stream.graphics-design.large",
   "stream.graphics-design.xlarge",
   "stream.graphics-pro.16xlarge",
   "stream.graphics-pro.4xlarge",
   "stream.graphics-pro.8xlarge",
   "stream.graphics.g4dn.12xlarge",
   "stream.graphics.g4dn.16xlarge",
   "stream.graphics.g4dn.2xlarge",
   "stream.graphics.g4dn.4xlarge",
   "stream.graphics.g4dn.8xlarge",
   "stream.graphics.g4dn.xlarge",
   "stream.graphics.g5.12xlarge",
   "stream.graphics.g5.16xlarge",
   "stream.graphics.g5.24xlarge",
   "stream.graphics.g5.2xlarge",
   "stream.graphics.g5.4xlarge",
   "stream.graphics.g5.8xlarge",
   "stream.graphics.g5.xlarge",
   "stream.memory.2xlarge",
   "stream.memory.4xlarge",
   "stream.memory.8xlarge",
   "stream.memory.large",
   "stream.memory.xlarge",
   "stream.memory.z1d.12xlarge",
   "stream.memory.z1d.2xlarge",
   "stream.memory.z1d.3xlarge",
   "stream.memory.z1d.6xlarge",
   "stream.memory.z1d.large",
   "stream.memory.z1d.xlarge",
   "stream.standard.2xlarge",
   "stream.standard.large",
   "stream.standard.medium",
   "stream.standard.small",
   "stream.standard.xlarge"
  ]
 },
 "eu-west-1": {
  "enum": [
   "stream.compute.2xlarge",
   "stream.compute.4xlarge",
   "stream.compute.8xlarge",
   "stream.compute.large",
   "stream.compute.xlarge",
   "stream.graphics-design.2xlarge",
   "stream.graphics-design.4xlarge",
   "stream.graphics-design.large",
   "stream.graphics-design.xlarge",
   "stream.graphics-pro.16xlarge",
   "stream.graphics-pro.4xlarge",
   "stream.graphics-pro.8xlarge",
   "stream.graphics.g4dn.12xlarge",
   "stream.graphics.g4dn.16xlarge",
   "stream.graphics.g4dn.2xlarge",
   "stream.graphics.g4dn.4xlarge",
   "stream.graphics.g4dn.8xlarge",
   "stream.graphics.g4dn.xlarge",
   "stream.graphics.g5.12xlarge",
   "stream.graphics.g5.16xlarge",
   "stream.graphics.g5.24xlarge",
   "stream.graphics.g5.2xlarge",
   "stream.graphics.g5.4xlarge",
   "stream.graphics.g5.8xlarge",
   "stream.graphics.g5.xlarge",
   "stream.memory.2xlarge",
   "stream.memory.4xlarge",
   "stream.memory.8xlarge",
   "stream.memory.large",
   "stream.memory.xlarge",
   "stream.memory.z1d.12xlarge",
   "stream.memory.z1d.2xlarge",
   "stream.memory.z1d.3xlarge",
   "stream.memory.z1d.6xlarge",
   "stream.memory.z1d.large",
   "stream.memory.z1d.xlarge",
   "stream.standard.2xlarge",
   "stream.standard.large",
   "stream.standard.medium",
   "stream.standard.small",
   "stream.standard.xlarge"
  ]
 },
 "eu-west-2": {
  "enum": [
   "stream.compute.2xlarge",
   "stream.compute.4xlarge",
   "stream.compute.8xlarge",
   "stream.compute.large",
   "stream.compute.xlarge",
   "stream.graphics-design.2xlarge",
   "stream.graphics-design.4xlarge",
   "stream.graphics-design.large",
   "stream.graphics-design.xlarge",
   "stream.graphics-pro.16xlarge",
   "stream.graphics-pro.4xlarge",
   "stream.graphics-pro.8xlarge",
   "stream.graphics.g4dn.12xlarge",
   "stream.graphics.g4dn.16xlarge",
   "stream.graphics.g4dn.2xlarge",
   "stream.graphics.g4dn.4xlarge",
   "stream.graphics.g4dn.8xlarge",
   "stream.graphics.g4dn.xlarge",
   "stream.graphics.g5.12xlarge",
   "stream.graphics.g5.16xlarge",
   "stream.graphics.g5.24xlarge",
   "stream.graphics.g5.2xlarge",
   "stream.graphics.g5.4xlarge",
   "stream.graphics.g5.8xlarge",
   "stream.graphics.g5.xlarge",
   "stream.memory.2xlarge",
   "stream.memory.4xlarge",
   "stream.memory.8xlarge",
   "stream.memory.large",
   "stream.memory.xlarge",
   "stream.memory.z1d.12xlarge",
   "stream.memory.z1d.2xlarge",
   "stream.memory.z1d.3xlarge",
   "stream.memory.z1d.6xlarge",
   "stream.memory.z1d.large",
   "stream.memory.z1d.xlarge",
   "stream.standard.2xlarge",
   "stream.standard.large",
   "stream.standard.medium",
   "stream.standard.small",
   "stream.standard.xlarge"
  ]
 },
 "eu-west-3": {
  "enum": [
   "stream.compute.2xlarge",
   "stream.compute.4xlarge",
   "stream.compute.8xlarge",
   "stream.compute.large",
   "stream.compute.xlarge",
   "stream.graphics-design.2xlarge",
   "stream.graphics-design.4xlarge",
   "stream.graphics-design.large",
   "stream.graphics-design.xlarge",
   "stream.graphics-pro.16xlarge",
   "stream.graphics-pro.4xlarge",
   "stream.graphics-pro.8xlarge",
   "stream.graphics.g4dn.12xlarge",
   "stream.graphics.g4dn.16xlarge",
   "stream.graphics.g4dn.2xlarge",
   "stream.graphics.g4dn.4xlarge",
   "stream.graphics.g4dn.8xlarge",
   "stream.graphics.g4dn.xlarge",
   "stream.graphics.g5.12xlarge",
   "stream.graphics.g5.16xlarge",
   "stream.graphics.g5.24xlarge",
   "stream.graphics.g5.2xlarge",
   "stream.graphics.g5.4xlarge",
   "stream.graphics.g5.8xlarge",
   "stream.graphics.g5.xlarge",
   "stream.memory.2xlarge",
   "stream.memory.4xlarge",
   "stream.memory.8xlarge",
   "stream.memory.large",
   "stream.memory.xlarge",
   "stream.memory.z1d.12xlarge",
   "stream.memory.z1d.2xlarge",
   "stream.memory.z1d.3xlarge",
   "stream.memory.z1d.6xlarge",
   "stream.memory.z1d.large",
   "stream.memory.z1d.xlarge",
   "stream.standard.2xlarge",
   "stream.standard.large",
   "stream.standard.medium",
   "stream.standard.small",
   "stream.standard.xlarge"
  ]
 },
 "sa-east-1": {
  "enum": [
   "stream.compute.2xlarge",
   "stream.compute.4xlarge",
   "stream.compute.8xlarge",
   "stream.compute.large",
   "stream.compute.xlarge",
   "stream.graphics-design.2xlarge",
   "stream.graphics-design.4xlarge",
   "stream.graphics-design.large",
   "stream.graphics-design.xlarge",
   "stream.graphics-pro.16xlarge",
   "stream.graphics-pro.4xlarge",
   "stream.graphics-pro.8xlarge",
   "stream.graphics.g4dn.12xlarge",
   "stream.graphics.g4dn.16xlarge",
   "stream.graphics.g4dn.2xlarge",
   "stream.graphics.g4dn.4xlarge",
   "stream.graphics.g4dn.8xlarge",
   "stream.graphics.g4dn.xlarge",
   "stream.graphics.g5.12xlarge",
   "stream.graphics.g5.16xlarge",
   "stream.graphics.g5.24xlarge",
   "stream.graphics.g5.2xlarge",
   "stream.graphics.g5.4xlarge",
   "stream.graphics.g5.8xlarge",
   "stream.graphics.g5.xlarge",
   "stream.memory.2xlarge",
   "stream.memory.4xlarge",
   "stream.memory.8xlarge",
   "stream.memory.large",
   "stream.memory.xlarge",
   "stream.memory.z1d.12xlarge",
   "stream.memory.z1d.2xlarge",
   "stream.memory.z1d.3xlarge",
   "stream.memory.z1d.6xlarge",
   "stream.memory.z1d.large",
   "stream.memory.z1d.xlarge",
   "stream.standard.2xlarge",
   "stream.standard.large",
   "stream.standard.medium",
   "stream.standard.small",
   "stream.standard.xlarge"
  ]
 },
 "us-east-1": {
  "enum": [
   "stream.compute.2xlarge",
   "stream.compute.4xlarge",
   "stream.compute.8xlarge",
   "stream.compute.large",
   "stream.compute.xlarge",
   "stream.graphics-design.2xlarge",
   "stream.graphics-design.4xlarge",
   "stream.graphics-design.large",
   "stream.graphics-design.xlarge",
   "stream.graphics-pro.16xlarge",
   "stream.graphics-pro.4xlarge",
   "stream.graphics-pro.8xlarge",
   "stream.graphics.g4dn.12xlarge",
   "stream.graphics.g4dn.16xlarge",
   "stream.graphics.g4dn.2xlarge",
   "stream.graphics.g4dn.4xlarge",
   "stream.graphics.g4dn.8xlarge",
   "stream.graphics.g4dn.xlarge",
   "stream.graphics.g5.12xlarge",
   "stream.graphics.g5.16xlarge",
   "stream.graphics.g5.24xlarge",
   "stream.graphics.g5.2xlarge",
   "stream.graphics.g5.4xlarge",
   "stream.graphics.g5.8xlarge",
   "stream.graphics.g5.xlarge",
   "stream.memory.2xlarge",
   "stream.memory.4xlarge",
   "stream.memory.8xlarge",
   "stream.memory.large",
   "stream.memory.xlarge",
   "stream.memory.z1d.12xlarge",
   "stream.memory.z1d.2xlarge",
   "stream.memory.z1d.3xlarge",
   "stream.memory.z1d.6xlarge",
   "stream.memory.z1d.large",
   "stream.memory.z1d.xlarge",
   "stream.standard.2xlarge",
   "stream.standard.large",
   "stream.standard.medium",
   "stream.standard.small",
   "stream.standard.xlarge"
  ]
 },
 "us-east-2": {
  "enum": [
   "stream.compute.2xlarge",
   "stream.compute.4xlarge",
   "stream.compute.8xlarge",
   "stream.compute.large",
   "stream.compute.xlarge",
   "stream.graphics-design.2xlarge",
   "stream.graphics-design.4xlarge",
   "stream.graphics-design.large",
   "stream.graphics-design.xlarge",
   "stream.graphics-pro.16xlarge",
   "stream.graphics-pro.4xlarge",
   "stream.graphics-pro.8xlarge",
   "stream.graphics.g4dn.12xlarge",
   "stream.graphics.g4dn.16xlarge",
   "stream.graphics.g4dn.2xlarge",
   "stream.graphics.g4dn.4xlarge",
   "stream.graphics.g4dn.8xlarge",
   "stream.graphics.g4dn.xlarge",
   "stream.graphics.g5.12xlarge",
   "stream.graphics.g5.16xlarge",
   "stream.graphics.g5.24xlarge",
   "stream.graphics.g5.2xlarge",
   "stream.graphics.g5.4xlarge",
   "stream.graphics.g5.8xlarge",
   "stream.graphics.g5.xlarge",
   "stream.memory.2xlarge",
   "stream.memory.4xlarge",
   "stream.memory.8xlarge",
   "stream.memory.large",
   "stream.memory.xlarge",
   "stream.memory.z1d.12xlarge",
   "stream.memory.z1d.2xlarge",
   "stream.memory.z1d.3xlarge",
   "stream.memory.z1d.6xlarge",
   "stream.memory.z1d.large",
   "stream.memory.z1d.xlarge",
   "stream.standard.2xlarge",
   "stream.standard.large",
   "stream.standard.medium",
   "stream.standard.small",
   "stream.standard.xlarge"
  ]
 },
 "us-gov-east-1": {
  "enum": [
   "stream.compute.2xlarge",
   "stream.compute.4xlarge",
   "stream.compute.8xlarge",
   "stream.compute.large",
   "stream.compute.xlarge",
   "stream.graphics-design.2xlarge",
   "stream.graphics-design.4xlarge",
   "stream.graphics-design.large",
   "stream.graphics-design.xlarge",
   "stream.graphics-pro.16xlarge",
   "stream.graphics-pro.4xlarge",
   "stream.graphics-pro.8xlarge",
   "stream.graphics.g4dn.12xlarge",
   "stream.graphics.g4dn.16xlarge",
   "stream.graphics.g4dn.2xlarge",
   "stream.graphics.g4dn.4xlarge",
   "stream.graphics.g4dn.8xlarge",
   "stream.graphics.g4dn.xlarge",
   "stream.graphics.g5.12xlarge",
   "stream.graphics.g5.16xlarge",
   "stream.graphics.g5.24xlarge",
   "stream.graphics.g5.2xlarge",
   "stream.graphics.g5.4xlarge",
   "stream.graphics.g5.8xlarge",
   "stream.graphics.g5.xlarge",
   "stream.memory.2xlarge",
   "stream.memory.4xlarge",
   "stream.memory.8xlarge",
   "stream.memory.large",
   "stream.memory.xlarge",
   "stream.memory.z1d.12xlarge",
   "stream.memory.z1d.2xlarge",
   "stream.memory.z1d.3xlarge",
   "stream.memory.z1d.6xlarge",
   "stream.memory.z1d.large",
   "stream.memory.z1d.xlarge",
   "stream.standard.2xlarge",
   "stream.standard.large",
   "stream.standard.medium",
   "stream.standard.small",
   "stream.standard.xlarge"
  ]
 },
 "us-gov-west-1": {
  "enum": [
   "stream.compute.2xlarge",
   "stream.compute.4xlarge",
   "stream.compute.8xlarge",
   "stream.compute.large",
   "stream.compute.xlarge",
   "stream.graphics-design.2xlarge",
   "stream.graphics-design.4xlarge",
   "stream.graphics-design.large",
   "stream.graphics-design.xlarge",
   "stream.graphics-pro.16xlarge",
   "stream.graphics-pro.4xlarge",
   "stream.graphics-pro.8xlarge",
   "stream.graphics.g4dn.12xlarge",
   "stream.graphics.g4dn.16xlarge",
   "stream.graphics.g4dn.2xlarge",
   "stream.graphics.g4dn.4xlarge",
   "stream.graphics.g4dn.8xlarge",
   "stream.graphics.g4dn.xlarge",
   "stream.graphics.g5.12xlarge",
   "stream.graphics.g5.16xlarge",
   "stream.graphics.g5.24xlarge",
   "stream.graphics.g5.2xlarge",
   "stream.graphics.g5.4xlarge",
   "stream.graphics.g5.8xlarge",
   "stream.graphics.g5.xlarge",
   "stream.memory.2xlarge",
   "stream.memory.4xlarge",
   "stream.memory.8xlarge",
   "stream.memory.large",
   "stream.memory.xlarge",
   "stream.memory.z1d.12xlarge",
   "stream.memory.z1d.2xlarge",
   "stream.memory.z1d.3xlarge",
   "stream.memory.z1d.6xlarge",
   "stream.memory.z1d.large",
   "stream.memory.z1d.xlarge",
   "stream.standard.2xlarge",
   "stream.standard.large",
   "stream.standard.medium",
   "stream.standard.small",
   "stream.standard.xlarge"
  ]
 },
 "us-west-2": {
  "enum": [
   "stream.compute.2xlarge",
   "stream.compute.4xlarge",
   "stream.compute.8xlarge",
   "stream.compute.large",
   "stream.compute.xlarge",
   "stream.graphics-design.2xlarge",
   "stream.graphics-design.4xlarge",
   "stream.graphics-design.large",
   "stream.graphics-design.xlarge",
   "stream.graphics-pro.16xlarge",
   "stream.graphics-pro.4xlarge",
   "stream.graphics-pro.8xlarge",
   "stream.graphics.g4dn.12xlarge",
   "stream.graphics.g4dn.16xlarge",
   "stream.graphics.g4dn.2xlarge",
   "stream.graphics.g4dn.4xlarge",
   "stream.graphics.g4dn.8xlarge",
   "stream.graphics.g4dn.xlarge",
   "stream.graphics.g5.12xlarge",
   "stream.graphics.g5.16xlarge",
   "stream.graphics.g5.24xlarge",
   "stream.graphics.g5.2xlarge",
   "stream.graphics.g5.4xlarge",
   "stream.graphics.g5.8xlarge",
   "stream.graphics.g5.xlarge",
   "stream.memory.2xlarge",
   "stream.memory.4xlarge",
   "stream.memory.8xlarge",
   "stream.memory.large",
   "stream.memory.xlarge",
   "stream.memory.z1d.12xlarge",
   "stream.memory.z1d.2xlarge",
   "stream.memory.z1d.3xlarge",
   "stream.memory.z1d.6xlarge",
   "stream.memory.z1d.large",
   "stream.memory.z1d.xlarge",
   "stream.standard.2xlarge",
   "stream.standard.large",
   "stream.standard.medium",
   "stream.standard.small",
   "stream.standard.xlarge"
  ]
 }
}
